pydependabot/__init__.py
pydependabot/consts.py
pydependabot/main.py
pydependabot/repository_vulnerablity_alert_node.py
pydependabot/repository_vulnerablity_alert_query.py
pydependabot/utils.py
pydependabot-0.8.dist-info/LICENSE.txt
pydependabot-0.8.dist-info/METADATA
pydependabot-0.8.dist-info/WHEEL
pydependabot-0.8.dist-info/top_level.txt
pydependabot-0.8.dist-info/RECORD
