Metadata-Version: 2.1
Name: pydependabot
Version: 0.8
Summary: A python library to query and manage github's dependabot alerts
Home-page: UNKNOWN
Author: Or1337 (Or Elias)
Author-email: <orelias.tm@gmail.com>
License: UNKNOWN
Keywords: python,Dependabot,github,security,open source security,pyDependabot,pydependabot,py-dependabot
Platform: UNKNOWN
Classifier: Development Status :: 2 - Pre-Alpha
Classifier: Intended Audience :: Developers
Classifier: Programming Language :: Python :: 3
Classifier: License :: OSI Approved :: MIT License
Classifier: Operating System :: Unix
Classifier: Operating System :: MacOS :: MacOS X
Classifier: Operating System :: Microsoft :: Windows
License-File: LICENSE.txt
Requires-Dist: gql
Requires-Dist: packaging
